{
    "/js/app.js": "/js/app.js",
    "/css/app.css": "/css/app.css",
    "/js/app.b50b9951a09305eaf845.hot-update.js": "/js/app.b50b9951a09305eaf845.hot-update.js",
    "/js/app.67096158060b4cd59f95.hot-update.js": "/js/app.67096158060b4cd59f95.hot-update.js",
    "/js/app.48b8a9f47a7200b91213.hot-update.js": "/js/app.48b8a9f47a7200b91213.hot-update.js",
    "/js/app.c1a73e313690e32360a7.hot-update.js": "/js/app.c1a73e313690e32360a7.hot-update.js",
    "/js/app.f1ce8892272f33fc932c.hot-update.js": "/js/app.f1ce8892272f33fc932c.hot-update.js",
    "/js/app.d0f5935f85fbe7e61ff8.hot-update.js": "/js/app.d0f5935f85fbe7e61ff8.hot-update.js",
    "/js/app.f44ae4d3688a9bdb471e.hot-update.js": "/js/app.f44ae4d3688a9bdb471e.hot-update.js",
    "/js/app.905a5cbac9d3602175bc.hot-update.js": "/js/app.905a5cbac9d3602175bc.hot-update.js",
    "/js/app.47f92efac595f6d50b6d.hot-update.js": "/js/app.47f92efac595f6d50b6d.hot-update.js",
    "/js/app.0bd41a0d91bde6a695c4.hot-update.js": "/js/app.0bd41a0d91bde6a695c4.hot-update.js",
    "/js/app.c9e1b69a579fa27160ad.hot-update.js": "/js/app.c9e1b69a579fa27160ad.hot-update.js",
    "/js/app.e55980ea02193b2adde9.hot-update.js": "/js/app.e55980ea02193b2adde9.hot-update.js",
    "/js/app.fe8c04e56b8be9e76be3.hot-update.js": "/js/app.fe8c04e56b8be9e76be3.hot-update.js",
    "/js/app.f5ece1bb509a9d61b335.hot-update.js": "/js/app.f5ece1bb509a9d61b335.hot-update.js",
    "/js/app.4cac8c4570a4a41aceed.hot-update.js": "/js/app.4cac8c4570a4a41aceed.hot-update.js",
    "/js/app.65c7f4733a8f34e88483.hot-update.js": "/js/app.65c7f4733a8f34e88483.hot-update.js",
    "/js/app.367704198ee8f6ffebad.hot-update.js": "/js/app.367704198ee8f6ffebad.hot-update.js",
    "/js/app.c68e2842c2df2eb833e5.hot-update.js": "/js/app.c68e2842c2df2eb833e5.hot-update.js",
    "/js/app.ab542d6011e2ffca3fe7.hot-update.js": "/js/app.ab542d6011e2ffca3fe7.hot-update.js",
    "/js/app.fe50f830cb35254778d3.hot-update.js": "/js/app.fe50f830cb35254778d3.hot-update.js",
    "/js/app.2ebccae75d11ad15c2e6.hot-update.js": "/js/app.2ebccae75d11ad15c2e6.hot-update.js",
    "/js/app.a5f21dcf6906a82d9b5f.hot-update.js": "/js/app.a5f21dcf6906a82d9b5f.hot-update.js",
    "/js/app.1e95c63bed70d3ce951f.hot-update.js": "/js/app.1e95c63bed70d3ce951f.hot-update.js",
    "/js/app.b09d75c661d4b5a55350.hot-update.js": "/js/app.b09d75c661d4b5a55350.hot-update.js",
    "/js/app.91886cd75132821674c9.hot-update.js": "/js/app.91886cd75132821674c9.hot-update.js",
    "/js/app.0db9822fd2351b88c759.hot-update.js": "/js/app.0db9822fd2351b88c759.hot-update.js",
    "/js/app.38e44bd43b554c1eeb77.hot-update.js": "/js/app.38e44bd43b554c1eeb77.hot-update.js",
    "/js/app.5c0a0db92030094d44fd.hot-update.js": "/js/app.5c0a0db92030094d44fd.hot-update.js",
    "/js/app.ddb19f7a573b195275c1.hot-update.js": "/js/app.ddb19f7a573b195275c1.hot-update.js",
    "/js/app.149acb6480b522aaf588.hot-update.js": "/js/app.149acb6480b522aaf588.hot-update.js",
    "/js/app.da985961d3267b55c7aa.hot-update.js": "/js/app.da985961d3267b55c7aa.hot-update.js",
    "/js/app.976d9d8fb263cfd2df7e.hot-update.js": "/js/app.976d9d8fb263cfd2df7e.hot-update.js",
    "/js/app.cda25cfbc3b61737b6d1.hot-update.js": "/js/app.cda25cfbc3b61737b6d1.hot-update.js",
    "/js/app.70ae73a034bb22b6b6e3.hot-update.js": "/js/app.70ae73a034bb22b6b6e3.hot-update.js",
    "/js/app.479732924355f6057070.hot-update.js": "/js/app.479732924355f6057070.hot-update.js",
    "/js/app.ca61e7dbc16316820ec3.hot-update.js": "/js/app.ca61e7dbc16316820ec3.hot-update.js",
    "/js/app.db1cac7ec3ae3eecf49c.hot-update.js": "/js/app.db1cac7ec3ae3eecf49c.hot-update.js",
    "/js/app.6484f5551f6f667a142f.hot-update.js": "/js/app.6484f5551f6f667a142f.hot-update.js",
    "/js/app.5312da7b963647e214d2.hot-update.js": "/js/app.5312da7b963647e214d2.hot-update.js",
    "/js/app.4c52d5d1ad190c7223dc.hot-update.js": "/js/app.4c52d5d1ad190c7223dc.hot-update.js",
    "/js/app.f2addf6f75e25821906a.hot-update.js": "/js/app.f2addf6f75e25821906a.hot-update.js",
    "/js/app.1685d0329ef15facc679.hot-update.js": "/js/app.1685d0329ef15facc679.hot-update.js",
    "/js/app.1d0a09fde636ccf7f33c.hot-update.js": "/js/app.1d0a09fde636ccf7f33c.hot-update.js",
    "/js/app.1708c6faa7af5dbafda7.hot-update.js": "/js/app.1708c6faa7af5dbafda7.hot-update.js",
    "/js/app.0f89ced95483145589ab.hot-update.js": "/js/app.0f89ced95483145589ab.hot-update.js",
    "/js/app.b062f319da128283b037.hot-update.js": "/js/app.b062f319da128283b037.hot-update.js",
    "/js/app.733e09098ada7f992a9c.hot-update.js": "/js/app.733e09098ada7f992a9c.hot-update.js",
    "/js/app.27cee02459d299ce4e95.hot-update.js": "/js/app.27cee02459d299ce4e95.hot-update.js",
    "/js/app.3b8db82b46a7caf24e31.hot-update.js": "/js/app.3b8db82b46a7caf24e31.hot-update.js",
    "/js/app.6645d92ece042adb2582.hot-update.js": "/js/app.6645d92ece042adb2582.hot-update.js",
    "/js/app.2e245ed69e9b5d11958b.hot-update.js": "/js/app.2e245ed69e9b5d11958b.hot-update.js",
    "/js/app.796a17fcad9d53bf999a.hot-update.js": "/js/app.796a17fcad9d53bf999a.hot-update.js",
    "/js/app.3a6fa31446f8d1e5b3bb.hot-update.js": "/js/app.3a6fa31446f8d1e5b3bb.hot-update.js",
    "/js/app.ddf039519943517f7ccb.hot-update.js": "/js/app.ddf039519943517f7ccb.hot-update.js",
    "/js/app.d41682c1479d9cc7dc25.hot-update.js": "/js/app.d41682c1479d9cc7dc25.hot-update.js",
    "/js/app.4463720c7e12dcb9a7d9.hot-update.js": "/js/app.4463720c7e12dcb9a7d9.hot-update.js",
    "/js/app.c57b1dbcfb37638a3c79.hot-update.js": "/js/app.c57b1dbcfb37638a3c79.hot-update.js",
    "/js/app.b9210ee1f0122f1df126.hot-update.js": "/js/app.b9210ee1f0122f1df126.hot-update.js",
    "/js/app.6dfbeb844f3677a25214.hot-update.js": "/js/app.6dfbeb844f3677a25214.hot-update.js",
    "/js/app.7d33e470adeb137fa010.hot-update.js": "/js/app.7d33e470adeb137fa010.hot-update.js",
    "/js/app.d9e5b2da53645d9b2538.hot-update.js": "/js/app.d9e5b2da53645d9b2538.hot-update.js",
    "/js/app.d7316ac41865f8765397.hot-update.js": "/js/app.d7316ac41865f8765397.hot-update.js",
    "/js/app.f91fdc7a68d689fa054c.hot-update.js": "/js/app.f91fdc7a68d689fa054c.hot-update.js",
    "/js/app.ae2f121bb32fa507218a.hot-update.js": "/js/app.ae2f121bb32fa507218a.hot-update.js",
    "/js/app.80424e07feba6a2c460f.hot-update.js": "/js/app.80424e07feba6a2c460f.hot-update.js",
    "/js/app.7546e1ddd6d67f1f3054.hot-update.js": "/js/app.7546e1ddd6d67f1f3054.hot-update.js",
    "/js/app.31bb9f95fee5b9fe0dde.hot-update.js": "/js/app.31bb9f95fee5b9fe0dde.hot-update.js",
    "/js/app.d126eb63c69d698d06d6.hot-update.js": "/js/app.d126eb63c69d698d06d6.hot-update.js",
    "/js/app.1cb45fc10c714e724071.hot-update.js": "/js/app.1cb45fc10c714e724071.hot-update.js",
    "/js/app.f9e1fdb5ccb215762993.hot-update.js": "/js/app.f9e1fdb5ccb215762993.hot-update.js",
    "/js/app.92fe17fb0a32bfad5528.hot-update.js": "/js/app.92fe17fb0a32bfad5528.hot-update.js",
    "/js/app.2fc52394aec25a9994f6.hot-update.js": "/js/app.2fc52394aec25a9994f6.hot-update.js",
    "/js/app.2e64017ad63f622a067b.hot-update.js": "/js/app.2e64017ad63f622a067b.hot-update.js",
    "/js/app.98e200d69d20dc66a3cc.hot-update.js": "/js/app.98e200d69d20dc66a3cc.hot-update.js",
    "/js/app.d2b5c1e4e6999b172f8d.hot-update.js": "/js/app.d2b5c1e4e6999b172f8d.hot-update.js",
    "/js/app.9f9eb5ccd8c4d75759d8.hot-update.js": "/js/app.9f9eb5ccd8c4d75759d8.hot-update.js",
    "/js/app.6be5b1e3fb17db87e1b4.hot-update.js": "/js/app.6be5b1e3fb17db87e1b4.hot-update.js",
    "/js/app.adf22383f35963acb095.hot-update.js": "/js/app.adf22383f35963acb095.hot-update.js",
    "/js/app.34ebeb60e10b9e50d51b.hot-update.js": "/js/app.34ebeb60e10b9e50d51b.hot-update.js",
    "/js/app.0869d48bf35d37c39d02.hot-update.js": "/js/app.0869d48bf35d37c39d02.hot-update.js",
    "/js/app.79fca03c69e0324ec6f9.hot-update.js": "/js/app.79fca03c69e0324ec6f9.hot-update.js",
    "/js/app.ede0bc239ffb9b148aee.hot-update.js": "/js/app.ede0bc239ffb9b148aee.hot-update.js",
    "/js/app.0fae83ad1a4bf0ef2f81.hot-update.js": "/js/app.0fae83ad1a4bf0ef2f81.hot-update.js",
    "/js/app.dea70b583f10c64ef48b.hot-update.js": "/js/app.dea70b583f10c64ef48b.hot-update.js",
    "/js/app.d498f393851f3cb7c233.hot-update.js": "/js/app.d498f393851f3cb7c233.hot-update.js",
    "/js/app.3ed4f40652166e5f4757.hot-update.js": "/js/app.3ed4f40652166e5f4757.hot-update.js",
    "/js/app.a56d45018ebd6bfc006e.hot-update.js": "/js/app.a56d45018ebd6bfc006e.hot-update.js",
    "/js/app.2752110e454ee8682fe5.hot-update.js": "/js/app.2752110e454ee8682fe5.hot-update.js",
    "/js/app.395dcd81b714c65ca2fd.hot-update.js": "/js/app.395dcd81b714c65ca2fd.hot-update.js",
    "/js/app.6f2d019f7e5d83f59b77.hot-update.js": "/js/app.6f2d019f7e5d83f59b77.hot-update.js",
    "/js/app.708aa1e4da44e65030f3.hot-update.js": "/js/app.708aa1e4da44e65030f3.hot-update.js",
    "/js/app.98b352044fdf8b42b589.hot-update.js": "/js/app.98b352044fdf8b42b589.hot-update.js",
    "/js/app.05d2f6d840e15a9c0044.hot-update.js": "/js/app.05d2f6d840e15a9c0044.hot-update.js",
    "/js/app.5f8ef8e389575e1bb042.hot-update.js": "/js/app.5f8ef8e389575e1bb042.hot-update.js",
    "/js/app.7375cf066a269caaccd1.hot-update.js": "/js/app.7375cf066a269caaccd1.hot-update.js",
    "/js/app.2f3d7006be481b2f44ed.hot-update.js": "/js/app.2f3d7006be481b2f44ed.hot-update.js",
    "/js/app.d8bfd87ee077b187adb9.hot-update.js": "/js/app.d8bfd87ee077b187adb9.hot-update.js",
    "/js/app.860c4593edfe226f3cca.hot-update.js": "/js/app.860c4593edfe226f3cca.hot-update.js",
    "/js/app.dca2c2ae090126e3cb03.hot-update.js": "/js/app.dca2c2ae090126e3cb03.hot-update.js",
    "/js/app.9fb093fa6230e3634bf6.hot-update.js": "/js/app.9fb093fa6230e3634bf6.hot-update.js",
    "/js/app.6b61492d13798d6c955b.hot-update.js": "/js/app.6b61492d13798d6c955b.hot-update.js",
    "/js/app.b66c55ee22bd48a378a9.hot-update.js": "/js/app.b66c55ee22bd48a378a9.hot-update.js",
    "/js/app.e0b57318d1d8fd23eb69.hot-update.js": "/js/app.e0b57318d1d8fd23eb69.hot-update.js",
    "/js/app.a4eb1c143beefbf6bee1.hot-update.js": "/js/app.a4eb1c143beefbf6bee1.hot-update.js",
    "/js/app.9a6f47420dd556c6edb2.hot-update.js": "/js/app.9a6f47420dd556c6edb2.hot-update.js",
    "/js/app.93c27a392b4e7c1dfbf0.hot-update.js": "/js/app.93c27a392b4e7c1dfbf0.hot-update.js",
    "/js/app.1d0a3b2aca115c71e8cf.hot-update.js": "/js/app.1d0a3b2aca115c71e8cf.hot-update.js",
    "/js/app.304141499119b4827c31.hot-update.js": "/js/app.304141499119b4827c31.hot-update.js",
    "/js/app.f444a888b8962894c906.hot-update.js": "/js/app.f444a888b8962894c906.hot-update.js",
    "/js/app.d1636204d204026770fa.hot-update.js": "/js/app.d1636204d204026770fa.hot-update.js",
    "/js/app.7a8d5f16bcea7e703129.hot-update.js": "/js/app.7a8d5f16bcea7e703129.hot-update.js",
    "/js/app.aa510cef11a4e7855631.hot-update.js": "/js/app.aa510cef11a4e7855631.hot-update.js",
    "/js/app.d32ab0bdf050a379289b.hot-update.js": "/js/app.d32ab0bdf050a379289b.hot-update.js",
    "/js/app.295980faac439df95794.hot-update.js": "/js/app.295980faac439df95794.hot-update.js",
    "/js/app.3eaaefcc053250015243.hot-update.js": "/js/app.3eaaefcc053250015243.hot-update.js",
    "/js/app.132a270637046fbca2b8.hot-update.js": "/js/app.132a270637046fbca2b8.hot-update.js",
    "/js/app.04c257fd41d45203166e.hot-update.js": "/js/app.04c257fd41d45203166e.hot-update.js",
    "/js/app.0c707345353660707d2d.hot-update.js": "/js/app.0c707345353660707d2d.hot-update.js",
    "/js/app.6fec7db9d569d67ab387.hot-update.js": "/js/app.6fec7db9d569d67ab387.hot-update.js",
    "/js/app.996c9ce1888288df8c28.hot-update.js": "/js/app.996c9ce1888288df8c28.hot-update.js",
    "/js/app.34ff9eb9072fca4b1c30.hot-update.js": "/js/app.34ff9eb9072fca4b1c30.hot-update.js",
    "/js/app.001d5ba460f520174dd2.hot-update.js": "/js/app.001d5ba460f520174dd2.hot-update.js",
    "/js/app.6ba3d6426c5a64a1d930.hot-update.js": "/js/app.6ba3d6426c5a64a1d930.hot-update.js",
    "/js/app.5c2587eaabb729d53d11.hot-update.js": "/js/app.5c2587eaabb729d53d11.hot-update.js",
    "/js/app.5e326669821df4b0a4c5.hot-update.js": "/js/app.5e326669821df4b0a4c5.hot-update.js",
    "/js/app.cc49e9af30bf4a712392.hot-update.js": "/js/app.cc49e9af30bf4a712392.hot-update.js",
    "/js/app.e0a4b148ca054044c0af.hot-update.js": "/js/app.e0a4b148ca054044c0af.hot-update.js",
    "/js/app.f57d3edfbb69d7a76108.hot-update.js": "/js/app.f57d3edfbb69d7a76108.hot-update.js",
    "/js/app.20e2d5aaacb0722c7ca8.hot-update.js": "/js/app.20e2d5aaacb0722c7ca8.hot-update.js",
    "/js/app.f8c9b4392bac1895979f.hot-update.js": "/js/app.f8c9b4392bac1895979f.hot-update.js",
    "/js/app.2a4c4ffa7e493acec4a5.hot-update.js": "/js/app.2a4c4ffa7e493acec4a5.hot-update.js",
    "/js/app.e98dc46dc807786ebc29.hot-update.js": "/js/app.e98dc46dc807786ebc29.hot-update.js",
    "/js/app.d24808501a41a318b4fd.hot-update.js": "/js/app.d24808501a41a318b4fd.hot-update.js",
    "/js/app.335719f2dcdefdba5097.hot-update.js": "/js/app.335719f2dcdefdba5097.hot-update.js",
    "/js/app.f84bc362326cde77e464.hot-update.js": "/js/app.f84bc362326cde77e464.hot-update.js",
    "/js/app.dbd386bc4f81c46b846c.hot-update.js": "/js/app.dbd386bc4f81c46b846c.hot-update.js",
    "/js/app.9888ddc09fa20e30d0f1.hot-update.js": "/js/app.9888ddc09fa20e30d0f1.hot-update.js",
    "/js/app.e69c666985a1c29017f9.hot-update.js": "/js/app.e69c666985a1c29017f9.hot-update.js",
    "/js/app.acfafb2d649a621f64f1.hot-update.js": "/js/app.acfafb2d649a621f64f1.hot-update.js",
    "/js/app.b812b88f36dbe81b57a9.hot-update.js": "/js/app.b812b88f36dbe81b57a9.hot-update.js",
    "/js/app.29094da934db99d84628.hot-update.js": "/js/app.29094da934db99d84628.hot-update.js",
    "/js/app.b3b1a351ae1c5117c25c.hot-update.js": "/js/app.b3b1a351ae1c5117c25c.hot-update.js",
    "/js/app.5dfd349526afd2f37ed2.hot-update.js": "/js/app.5dfd349526afd2f37ed2.hot-update.js",
    "/js/app.d730e4c6d27ae8d9dfeb.hot-update.js": "/js/app.d730e4c6d27ae8d9dfeb.hot-update.js",
    "/js/app.63cca57324823878cea2.hot-update.js": "/js/app.63cca57324823878cea2.hot-update.js",
    "/js/app.bfc4dd3ec9cb22ebc485.hot-update.js": "/js/app.bfc4dd3ec9cb22ebc485.hot-update.js",
    "/js/app.a57d7bce2d89ddf7c735.hot-update.js": "/js/app.a57d7bce2d89ddf7c735.hot-update.js",
    "/js/app.0916b5fdabf8c1847625.hot-update.js": "/js/app.0916b5fdabf8c1847625.hot-update.js",
    "/js/app.87cf47ce07436f142460.hot-update.js": "/js/app.87cf47ce07436f142460.hot-update.js",
    "/js/app.d3b5f56c8f912806dfad.hot-update.js": "/js/app.d3b5f56c8f912806dfad.hot-update.js",
    "/js/app.e6182d3fb9b823601138.hot-update.js": "/js/app.e6182d3fb9b823601138.hot-update.js",
    "/js/app.0d658f8cb09803c4f1a0.hot-update.js": "/js/app.0d658f8cb09803c4f1a0.hot-update.js",
    "/js/app.65ef6603f094f4093a75.hot-update.js": "/js/app.65ef6603f094f4093a75.hot-update.js",
    "/js/app.256c227f41e676cf9507.hot-update.js": "/js/app.256c227f41e676cf9507.hot-update.js",
    "/js/app.6364201ee94e1fee5bf3.hot-update.js": "/js/app.6364201ee94e1fee5bf3.hot-update.js",
    "/js/app.802478af7c962fe173fe.hot-update.js": "/js/app.802478af7c962fe173fe.hot-update.js",
    "/js/app.4173484795fd5cdff489.hot-update.js": "/js/app.4173484795fd5cdff489.hot-update.js",
    "/js/app.637ec5bb77d720b978b3.hot-update.js": "/js/app.637ec5bb77d720b978b3.hot-update.js",
    "/js/app.fbd5eb3a7468107d42e3.hot-update.js": "/js/app.fbd5eb3a7468107d42e3.hot-update.js",
    "/js/app.cd99a2ab6661e33bd8b7.hot-update.js": "/js/app.cd99a2ab6661e33bd8b7.hot-update.js",
    "/js/app.453184a5cc71b2f7cacf.hot-update.js": "/js/app.453184a5cc71b2f7cacf.hot-update.js",
    "/js/app.265969daa5de7fab48b9.hot-update.js": "/js/app.265969daa5de7fab48b9.hot-update.js",
    "/js/app.96721811a2b72ac6c5f4.hot-update.js": "/js/app.96721811a2b72ac6c5f4.hot-update.js",
    "/js/app.c21665bea4d6206ee6ef.hot-update.js": "/js/app.c21665bea4d6206ee6ef.hot-update.js",
    "/js/app.82daef07357c90311446.hot-update.js": "/js/app.82daef07357c90311446.hot-update.js",
    "/js/app.678547e1c9678f5e981a.hot-update.js": "/js/app.678547e1c9678f5e981a.hot-update.js",
    "/js/app.fe41bc08e335b05595a5.hot-update.js": "/js/app.fe41bc08e335b05595a5.hot-update.js",
    "/js/app.74170c0401ffe870fe33.hot-update.js": "/js/app.74170c0401ffe870fe33.hot-update.js",
    "/js/app.04967a49541e1311bce3.hot-update.js": "/js/app.04967a49541e1311bce3.hot-update.js",
    "/js/app.28cfa54d75ec59cbba53.hot-update.js": "/js/app.28cfa54d75ec59cbba53.hot-update.js",
    "/js/app.22cea4ec2cdf7792b4bf.hot-update.js": "/js/app.22cea4ec2cdf7792b4bf.hot-update.js",
    "/js/app.1a92d2191cc3533ba674.hot-update.js": "/js/app.1a92d2191cc3533ba674.hot-update.js",
    "/js/app.0c6ffdfa71471c8dfe74.hot-update.js": "/js/app.0c6ffdfa71471c8dfe74.hot-update.js",
    "/js/app.3ab5de88ed84ea43d40f.hot-update.js": "/js/app.3ab5de88ed84ea43d40f.hot-update.js",
    "/js/app.d768bcb68b7893552840.hot-update.js": "/js/app.d768bcb68b7893552840.hot-update.js",
    "/js/app.8f1493330b28398a23e6.hot-update.js": "/js/app.8f1493330b28398a23e6.hot-update.js",
    "/js/app.977e30c1dab172773752.hot-update.js": "/js/app.977e30c1dab172773752.hot-update.js",
    "/js/app.b40209ef03535eba284d.hot-update.js": "/js/app.b40209ef03535eba284d.hot-update.js",
    "/js/app.97721e9de35eaa45563d.hot-update.js": "/js/app.97721e9de35eaa45563d.hot-update.js",
    "/js/app.1df23a4bcf008cfc3e5d.hot-update.js": "/js/app.1df23a4bcf008cfc3e5d.hot-update.js",
    "/js/app.e323cb6f93317277bc5e.hot-update.js": "/js/app.e323cb6f93317277bc5e.hot-update.js",
    "/js/app.21bc34c009049e512496.hot-update.js": "/js/app.21bc34c009049e512496.hot-update.js",
    "/js/app.08833eba2ef5b2a0c109.hot-update.js": "/js/app.08833eba2ef5b2a0c109.hot-update.js",
    "/js/app.89433e4af4b61303f221.hot-update.js": "/js/app.89433e4af4b61303f221.hot-update.js",
    "/js/app.b0544d6796a06a2386b1.hot-update.js": "/js/app.b0544d6796a06a2386b1.hot-update.js",
    "/js/app.340fcde1966ac125574f.hot-update.js": "/js/app.340fcde1966ac125574f.hot-update.js",
    "/js/app.b511a2ac695552829b86.hot-update.js": "/js/app.b511a2ac695552829b86.hot-update.js",
    "/js/app.5d8c00a14d8186242183.hot-update.js": "/js/app.5d8c00a14d8186242183.hot-update.js",
    "/js/app.30f7f08d34b371fedc3d.hot-update.js": "/js/app.30f7f08d34b371fedc3d.hot-update.js",
    "/js/app.4bfbbda743acdc2d675f.hot-update.js": "/js/app.4bfbbda743acdc2d675f.hot-update.js",
    "/js/app.eabd1cdcae0c4a6f6cf3.hot-update.js": "/js/app.eabd1cdcae0c4a6f6cf3.hot-update.js",
    "/js/app.9f6f71b0e729f62cfff2.hot-update.js": "/js/app.9f6f71b0e729f62cfff2.hot-update.js",
    "/js/app.5d150d0c52b0d7483f2d.hot-update.js": "/js/app.5d150d0c52b0d7483f2d.hot-update.js"
}
